faq/__init__.py
faq/admin.py
faq/apps.py
faq/models.py
faq/serializers.py
faq/tests.py
faq/urls.py
faq/views.py
faq/migrations/0001_initial.py
faq/migrations/0002_faq_order.py
faq/migrations/0003_category_order.py
faq/migrations/__init__.py
bulu_faq-0.3.dist-info/LICENSE
bulu_faq-0.3.dist-info/METADATA
bulu_faq-0.3.dist-info/WHEEL
bulu_faq-0.3.dist-info/top_level.txt
bulu_faq-0.3.dist-info/RECORD
